Topsis_Raghav_102003274/102003274.py
Topsis_Raghav_102003274/_init_.py
Topsis_Raghav_102003274-0.1.dist-info/METADATA
Topsis_Raghav_102003274-0.1.dist-info/WHEEL
Topsis_Raghav_102003274-0.1.dist-info/top_level.txt
Topsis_Raghav_102003274-0.1.dist-info/RECORD
